Metadata-Version: 2.1
Name: square-cloud-test-lucas
Version: 0.0.1
Summary: Implementacao da api da square cloud não oficial
Home-page: UNKNOWN
Author: Lucas Alves
Author-email: lucasal072@gmail.com
License: MIT License
Keywords: square_cloud_lucas_test
Platform: UNKNOWN
